{
    "ruote": [
        {
            "ruota": "Bari",
            "ambo": [
                7,
                25
            ],
            "score": 1448,
            "ultima_estrazione": [
                45,
                77,
                23,
                71,
                83
            ],
            "colpi_rimanenti": 1
        },
        {
            "ruota": "Cagliari",
            "ambo": [
                26,
                53
            ],
            "score": 1460,
            "ultima_estrazione": [
                32,
                55,
                16,
                31,
                22
            ],
            "colpi_rimanenti": 1
        },
        {
            "ruota": "Firenze",
            "ambo": [
                7,
                34
            ],
            "score": 1448,
            "ultima_estrazione": [
                40,
                37,
                50,
                42,
                86
            ],
            "colpi_rimanenti": 1
        },
        {
            "ruota": "Genova",
            "ambo": [
                11,
                38
            ],
            "score": 1448,
            "ultima_estrazione": [
                65,
                69,
                52,
                36,
                27
            ],
            "colpi_rimanenti": 4
        },
        {
            "ruota": "Milano",
            "ambo": [
                56,
                83
            ],
            "score": 1460,
            "ultima_estrazione": [
                59,
                56,
                79,
                37,
                64
            ],
            "colpi_rimanenti": 5
        },
        {
            "ruota": "Napoli",
            "ambo": [
                9,
                90
            ],
            "score": 1448,
            "ultima_estrazione": [
                8,
                9,
                43,
                71,
                28
            ],
            "colpi_rimanenti": 5
        },
        {
            "ruota": "Palermo",
            "ambo": [
                6,
                42
            ],
            "score": 1448,
            "ultima_estrazione": [
                46,
                79,
                55,
                1,
                67
            ],
            "colpi_rimanenti": 4
        },
        {
            "ruota": "Roma",
            "ambo": [
                4,
                31
            ],
            "score": 1448,
            "ultima_estrazione": [
                87,
                71,
                59,
                1,
                89
            ],
            "colpi_rimanenti": 2
        },
        {
            "ruota": "Torino",
            "ambo": [
                5,
                86
            ],
            "score": 1448,
            "ultima_estrazione": [
                51,
                38,
                48,
                22,
                31
            ],
            "colpi_rimanenti": 2
        },
        {
            "ruota": "Venezia",
            "ambo": [
                23,
                59
            ],
            "score": 1460,
            "ultima_estrazione": [
                76,
                56,
                16,
                52,
                33
            ],
            "colpi_rimanenti": 4
        }
    ],
    "jolly": [
        {
            "ruota": "Milano",
            "ambo": [
                56,
                83
            ],
            "score": 1460,
            "ultima_estrazione": [
                59,
                56,
                79,
                37,
                64
            ],
            "colpi_rimanenti": 5
        },
        {
            "ruota": "Venezia",
            "ambo": [
                23,
                59
            ],
            "score": 1460,
            "ultima_estrazione": [
                76,
                56,
                16,
                52,
                33
            ],
            "colpi_rimanenti": 4
        },
        {
            "ruota": "Cagliari",
            "ambo": [
                26,
                53
            ],
            "score": 1460,
            "ultima_estrazione": [
                32,
                55,
                16,
                31,
                22
            ],
            "colpi_rimanenti": 1
        }
    ],
    "ambo_forte": [
        {
            "ruota": "Milano",
            "ambo": [
                56,
                83
            ],
            "score": 1460,
            "ultima_estrazione": [
                59,
                56,
                79,
                37,
                64
            ],
            "colpi_rimanenti": 5
        },
        {
            "ruota": "Venezia",
            "ambo": [
                23,
                59
            ],
            "score": 1460,
            "ultima_estrazione": [
                76,
                56,
                16,
                52,
                33
            ],
            "colpi_rimanenti": 4
        },
        {
            "ruota": "Cagliari",
            "ambo": [
                26,
                53
            ],
            "score": 1460,
            "ultima_estrazione": [
                32,
                55,
                16,
                31,
                22
            ],
            "colpi_rimanenti": 1
        },
        {
            "ruota": "Bari",
            "ambo": [
                7,
                25
            ],
            "score": 1448,
            "ultima_estrazione": [
                45,
                77,
                23,
                71,
                83
            ],
            "colpi_rimanenti": 1
        },
        {
            "ruota": "Firenze",
            "ambo": [
                7,
                34
            ],
            "score": 1448,
            "ultima_estrazione": [
                40,
                37,
                50,
                42,
                86
            ],
            "colpi_rimanenti": 1
        }
    ],
    "previsioni_attive": [
        {
            "ruota": "Bari",
            "ambo": [
                7,
                25
            ],
            "score": 1448,
            "ultima_estrazione": [
                45,
                77,
                23,
                71,
                83
            ],
            "colpi_rimanenti": 1
        },
        {
            "ruota": "Firenze",
            "ambo": [
                7,
                34
            ],
            "score": 1448,
            "ultima_estrazione": [
                40,
                37,
                50,
                42,
                86
            ],
            "colpi_rimanenti": 1
        },
        {
            "ruota": "Milano",
            "ambo": [
                56,
                83
            ],
            "score": 1460,
            "ultima_estrazione": [
                59,
                56,
                79,
                37,
                64
            ],
            "colpi_rimanenti": 5
        },
        {
            "ruota": "Napoli",
            "ambo": [
                9,
                90
            ],
            "score": 1448,
            "ultima_estrazione": [
                8,
                9,
                43,
                71,
                28
            ],
            "colpi_rimanenti": 5
        },
        {
            "ruota": "Palermo",
            "ambo": [
                6,
                42
            ],
            "score": 1448,
            "ultima_estrazione": [
                46,
                79,
                55,
                1,
                67
            ],
            "colpi_rimanenti": 4
        },
        {
            "ruota": "Roma",
            "ambo": [
                4,
                31
            ],
            "score": 1448,
            "ultima_estrazione": [
                87,
                71,
                59,
                1,
                89
            ],
            "colpi_rimanenti": 2
        },
        {
            "ruota": "Torino",
            "ambo": [
                5,
                86
            ],
            "score": 1448,
            "ultima_estrazione": [
                51,
                38,
                48,
                22,
                31
            ],
            "colpi_rimanenti": 2
        },
        {
            "ruota": "Venezia",
            "ambo": [
                23,
                59
            ],
            "score": 1460,
            "ultima_estrazione": [
                76,
                56,
                16,
                52,
                33
            ],
            "colpi_rimanenti": 4
        },
        {
            "ruota": "Cagliari",
            "ambo": [
                26,
                53
            ],
            "score": 1460,
            "ultima_estrazione": [
                32,
                55,
                16,
                31,
                22
            ],
            "colpi_rimanenti": 1
        },
        {
            "ruota": "Genova",
            "ambo": [
                11,
                38
            ],
            "score": 1448,
            "ultima_estrazione": [
                65,
                69,
                52,
                36,
                27
            ],
            "colpi_rimanenti": 4
        }
    ]
}